AUTHORS.rst
CHANGES.rst
LICENSE.txt
MANIFEST.in
README.rst
setup.py
django_refinery.egg-info/PKG-INFO
django_refinery.egg-info/SOURCES.txt
django_refinery.egg-info/dependency_links.txt
django_refinery.egg-info/not-zip-safe
django_refinery.egg-info/requires.txt
django_refinery.egg-info/top_level.txt
docs/Makefile
docs/conf.py
docs/history.rst
docs/index.rst
docs/install.rst
docs/integration.rst
docs/tests.rst
docs/usage.rst
docs/ref/filters.rst
docs/ref/widgets.rst
refinery/__init__.py
refinery/fields.py
refinery/filters.py
refinery/filtertool.py
refinery/models.py
refinery/views.py
refinery/widgets.py