Metadata-Version: 1.0
Name: django-refinery
Version: 0.1
Summary: Django-refinery is a reusable Django application for allowing users to filter queryset dynamically.
Home-page: http://github.com/nkryptic/django-refinery
Author: Jacob Radford
Author-email: nkryptic@gmail.com
License: BSD
Keywords: django,refine,filter,models,querysets,forms
Platform: UNKNOWN
Classifier: Development Status :: 3 - Alpha
Classifier: Environment :: Web Environment
Classifier: Intended Audience :: Developers
Classifier: License :: OSI Approved :: BSD License
Classifier: Operating System :: OS Independent
Classifier: Programming Language :: Python
Classifier: Framework :: Django
